{
  "_comment": "Map short nicknames to exact YNAB category names. Case-insensitive on input.",
  "_instructions": "Add or edit shortcuts here. The value must match the YNAB category name exactly.",

"[Basic Expenses - Housing]  'Mortgage - 4000 Kaywood Court'"  :  "[Basic Expenses - Housing]  'Mortgage - 4000 Kaywood Court'",
"mortgage"  :  "[Basic Expenses - Housing]  'Mortgage - 4000 Kaywood Court'",
"mort"  :  "[Basic Expenses - Housing]  'Mortgage - 4000 Kaywood Court'",

"[Basic Expenses - Health Care]  'Medical - Other'"  :  "[Basic Expenses - Health Care]  'Medical - Other'",
"[Basic Expenses - Health Care]  'Medical - Optical'"  :  "[Basic Expenses - Health Care]  'Medical - Optical'",
"med optical"  :  "[Basic Expenses - Health Care]  'Medical - Optical'",
"[Basic Expenses - Health Care]  'Medical - Cosmetic'"  :  "[Basic Expenses - Health Care]  'Medical - Cosmetic'",
"med cosmetic"  :  "[Basic Expenses - Health Care]  'Medical - Cosmetic'",
"[Basic Expenses - Health Care]  'Medical - Dental'"  :  "[Basic Expenses - Health Care]  'Medical - Dental'",
"med dental"  :  "[Basic Expenses - Health Care]  'Medical - Dental'",
"[Basic Expenses - Health Care]  'Medical - Non HSA'"  :  "[Basic Expenses - Health Care]  'Medical - Non HSA'",
"medical"  :  "[Basic Expenses - Health Care]  'Medical - Non HSA'",
"med"  :  "[Basic Expenses - Health Care]  'Medical - Non HSA'",
"[Basic Expenses - Health Care]  'Medical - HSAs'"  :  "[Basic Expenses - Health Care]  'Medical - HSAs'",
"[Basic Expenses - Health Care]  'Medical - Pharmaceutical'"  :  "[Basic Expenses - Health Care]  'Medical - Pharmaceutical'",
"med pharm"  :  "[Basic Expenses - Health Care]  'Medical - Pharmaceutical'",
"pharma"  :  "[Basic Expenses - Health Care]  'Medical - Pharmaceutical'",
"pharm"  :  "[Basic Expenses - Health Care]  'Medical - Pharmaceutical'",

"[Basic Expenses - Rental Home]  'Mortgage - 17008 WTR'"  :  "[Basic Expenses - Rental Home]  'Mortgage - 17008 WTR'",
"mortgage wtr"  :  "[Basic Expenses - Rental Home]  'Mortgage - 17008 WTR'",
"mort wtr"  :  "[Basic Expenses - Rental Home]  'Mortgage - 17008 WTR'",
"mortwtr"  :  "[Basic Expenses - Rental Home]  'Mortgage - 17008 WTR'",

"[Basic Expenses - Rental Home]  'Rental Maintenance - 17008 WTR'"  :  "[Basic Expenses - Rental Home]  'Rental Maintenance - 17008 WTR'",
"maint wtr"  :  "[Basic Expenses - Rental Home]  'Rental Maintenance - 17008 WTR'",
"maintwtr"  :  "[Basic Expenses - Rental Home]  'Rental Maintenance - 17008 WTR'",

"[Basic Expenses - Rental Home]  'Utilities & POA - 17008 WTR'"  :  "[Basic Expenses - Rental Home]  'Utilities & POA - 17008 WTR'",
"util wtr"  :  "[Basic Expenses - Rental Home]  'Utilities & POA - 17008 WTR'",
"utilwtr"  :  "[Basic Expenses - Rental Home]  'Utilities & POA - 17008 WTR'",

"[Goal - Children (Non-Academic)]  'Sophie - Auto '"  :  "[Goal - Children (Non-Academic)]  'Sophie - Auto '",
"[Goal - Children (Non-Academic)]  'Fraud'"  :  "[Goal - Children (Non-Academic)]  'Fraud'",
"[Goal - Children (Non-Academic)]  'Chris - Europe Summer 24'"  :  "[Goal - Children (Non-Academic)]  'Chris - Europe Summer 24'",
"[Goal - Children (Non-Academic)]  'Children - Undesignated'"  :  "[Goal - Children (Non-Academic)]  'Children - Undesignated'",
"[Goal - Children (Non-Academic)]  'Sophie - wrong card'"  :  "[Goal - Children (Non-Academic)]  'Sophie - wrong card'",
"[Goal - Children (Non-Academic)]  'Chris - wrong card'"  :  "[Goal - Children (Non-Academic)]  'Chris - wrong card'",
"[Goal - Children (Non-Academic)]  'Children - Gifts'"  :  "[Goal - Children (Non-Academic)]  'Children - Gifts'",
"[Goal - Children (Non-Academic)]  'Allowance'"  :  "[Goal - Children (Non-Academic)]  'Allowance'",
"[Goal - Children (Non-Academic)]  'Clothing'"  :  "[Goal - Children (Non-Academic)]  'Clothing'",
"[Goal - Children (Non-Academic)]  'Clothing - Chris'"  :  "[Goal - Children (Non-Academic)]  'Clothing - Chris'",
"[Goal - Children (Non-Academic)]  'Clothing - Sophie'"  :  "[Goal - Children (Non-Academic)]  'Clothing - Sophie'",
"[Goal - Children (Non-Academic)]  'Misc'"  :  "[Goal - Children (Non-Academic)]  'Misc'",
"[Goal - Children (Non-Academic)]  'Misc - Sophie'"  :  "[Goal - Children (Non-Academic)]  'Misc - Sophie'",
"[Goal - Children (Non-Academic)]  'Project Support'"  :  "[Goal - Children (Non-Academic)]  'Project Support'",
"[Goal - Children (Non-Academic)]  'Project Support - Refundable'"  :  "[Goal - Children (Non-Academic)]  'Project Support - Refundable'",
"[Goal - Children (Non-Academic)]  'Services'"  :  "[Goal - Children (Non-Academic)]  'Services'",
"[Goal - Children (Non-Academic)]  'Skin Care'"  :  "[Goal - Children (Non-Academic)]  'Skin Care'",
"[Goal - Children (Non-Academic)]  'Travel'"  :  "[Goal - Children (Non-Academic)]  'Travel'",
"[Goal - Children (Non-Academic)]  'Transportation'"  :  "[Goal - Children (Non-Academic)]  'Transportation'",
"[Goal - Chris on Payroll]  'Chris Money'"  :  "[Goal - Chris on Payroll]  'Chris Money'",
"[Goal - Chris on Payroll]  'Chris - USC - Auto'"  :  "[Goal - Chris on Payroll]  'Chris - USC - Auto'",
"[Goal - Chris on Payroll]  'Chris - USC - Books and Supplies'"  :  "[Goal - Chris on Payroll]  'Chris - USC - Books and Supplies'",
"[Goal - Chris on Payroll]  'Chris - USC - Fraternity Related'"  :  "[Goal - Chris on Payroll]  'Chris - USC - Fraternity Related'",
"[Goal - Chris on Payroll]  'Chris - USC - Misc'"  :  "[Goal - Chris on Payroll]  'Chris - USC - Misc'",
"[Goal - Chris on Payroll]  'Chris - USC - Room and Board'"  :  "[Goal - Chris on Payroll]  'Chris - USC - Room and Board'",
"chris rent"  :  "[Goal - Chris on Payroll]  'Chris - USC - Room and Board'",
"cj rent"  :  "[Goal - Chris on Payroll]  'Chris - USC - Room and Board'",
"cjrent"  :  "[Goal - Chris on Payroll]  'Chris - USC - Room and Board'",
"[Goal - Chris on Payroll]  'Chris - USC - Tuition and Fees'"  :  "[Goal - Chris on Payroll]  'Chris - USC - Tuition and Fees'",
"[Goal - Travel]  'Travel - Spring plus Sophie Bday'"  :  "[Goal - Travel]  'Travel - Spring plus Sophie Bday'",
"[Goal - Travel]  'Travel - Summer'"  :  "[Goal - Travel]  'Travel - Summer'",
"[Goal - Travel]  'Travel - Summer Malibu'"  :  "[Goal - Travel]  'Travel - Summer Malibu'",
"[Goal - Travel]  'Travel - Fall'"  :  "[Goal - Travel]  'Travel - Fall'",
"[Goal - Travel]  'Travel - Thanksgiving'"  :  "[Goal - Travel]  'Travel - Thanksgiving'",
"[Goal - Travel]  'Travel - Winter'"  :  "[Goal - Travel]  'Travel - Winter'",
"[Goal - Travel]  'Travel - Chris Related'"  :  "[Goal - Travel]  'Travel - Chris Related'",
"[Goal - Travel]  'Travel - Sophie Related'"  :  "[Goal - Travel]  'Travel - Sophie Related'",
"[Goal - Travel]  'Travel - Yoga'"  :  "[Goal - Travel]  'Travel - Yoga'",
"[Goal - Travel]  'Travel - Other'"  :  "[Goal - Travel]  'Travel - Other'",
"[Goal - Wedding #1]  'Other Wedding expenses'"  :  "[Goal - Wedding #1]  'Other Wedding expenses'",
"wedding"  :  "[Goal - Wedding #1]  'Other Wedding expenses'",
"[Goal - Wedding #1]  'Sophie - Wedding'"  :  "[Goal - Wedding #1]  'Sophie - Wedding'",
"[Goal - Home Improvement]  'Major Home Purchases'"  :  "[Goal - Home Improvement]  'Major Home Purchases'",
"[Goal - Home Improvement]  'Landscaping and Exterior Maintenance'"  :  "[Goal - Home Improvement]  'Landscaping and Exterior Maintenance'",
"big landscaping"  :  "[Goal - Home Improvement]  'Landscaping and Exterior Maintenance'",
"big land"  :  "[Goal - Home Improvement]  'Landscaping and Exterior Maintenance'",
"big lawn"  :  "[Goal - Home Improvement]  'Landscaping and Exterior Maintenance'",
"[Living Expenses - Auto/Transport]  'Auto Parking'"  :  "[Living Expenses - Auto/Transport]  'Auto Parking'",
"parking"  :  "[Living Expenses - Auto/Transport]  'Auto Parking'",
"park"  :  "[Living Expenses - Auto/Transport]  'Auto Parking'",
"[Living Expenses - Auto/Transport]  'Auto Fuel'"  :  "[Living Expenses - Auto/Transport]  'Auto Fuel'",
"auto fuel"  :  "[Living Expenses - Auto/Transport]  'Auto Fuel'",
"gas"  :  "[Living Expenses - Auto/Transport]  'Auto Fuel'",
"[Living Expenses - Auto/Transport]  'Auto Legal'"  :  "[Living Expenses - Auto/Transport]  'Auto Legal'",
"[Living Expenses - Auto/Transport]  'Auto Maintenance'"  :  "[Living Expenses - Auto/Transport]  'Auto Maintenance'",
"auto maintenance"  :  "[Living Expenses - Auto/Transport]  'Auto Maintenance'",
"auto maint"  :  "[Living Expenses - Auto/Transport]  'Auto Maintenance'",
"[Living Expenses - Auto/Transport]  'Uber/Lyft/Taxi'"  :  "[Living Expenses - Auto/Transport]  'Uber/Lyft/Taxi'",
"uber"  :  "[Living Expenses - Auto/Transport]  'Uber/Lyft/Taxi'",
"lyft"  :  "[Living Expenses - Auto/Transport]  'Uber/Lyft/Taxi'",
"taxi"  :  "[Living Expenses - Auto/Transport]  'Uber/Lyft/Taxi'",  
"[Living Expenses - Household]  'Home Furnishings'"  :  "[Living Expenses - Household]  'Home Furnishings'",
"home furnishings"  :  "[Living Expenses - Household]  'Home Furnishings'",
"furnishings"  :  "[Living Expenses - Household]  'Home Furnishings'",
"furnish"  :  "[Living Expenses - Household]  'Home Furnishings'",
"[Living Expenses - Household]  'Home Lawn and Garden'"  :  "[Living Expenses - Household]  'Home Lawn and Garden'",
"lawn"  :  "[Living Expenses - Household]  'Home Lawn and Garden'",
"flavian"  :  "[Living Expenses - Household]  'Home Lawn and Garden'",
"[Living Expenses - Household]  'Home Maintenance'"  :  "[Living Expenses - Household]  'Home Maintenance'",
"home maintenance"  :  "[Living Expenses - Household]  'Home Maintenance'",
"home maint"  :  "[Living Expenses - Household]  'Home Maintenance'",
"[Living Expenses - Household]  'Utilities - Electric'"  :  "[Living Expenses - Household]  'Utilities - Electric'",
"electric"  :  "[Living Expenses - Household]  'Utilities - Electric'",
"power"  :  "[Living Expenses - Household]  'Utilities - Electric'",
"[Living Expenses - Household]  'Utilities - Exterminator'"  :  "[Living Expenses - Household]  'Utilities - Exterminator'",
"exterminator"  :  "[Living Expenses - Household]  'Utilities - Exterminator'",
"[Living Expenses - Household]  'Utilities - eaneaning'"  :  "[Living Expenses - Household]  'Utilities - Housecleaning'",
"housecleaning"  :  "[Living Expenses - Household]  'Utilities - Housecleaning'",
"house cleaning"  :  "[Living Expenses - Household]  'Utilities - Housecleaning'",
"chela"  :  "[Living Expenses - Household]  'Utilities - Housecleaning'",
"[Living Expenses - Household]  'Utilities - Internet'"  :  "[Living Expenses - Household]  'Utilities - Internet'",
"internet"  :  "[Living Expenses - Household]  'Utilities - Internet'",
"[Living Expenses - Household]  'Utilities - Pool Maintenance'"  :  "[Living Expenses - Household]  'Utilities - Pool Maintenance'",
"pool maintenance"  :  "[Living Expenses - Household]  'Utilities - Pool Maintenance'",
"pool maint"  :  "[Living Expenses - Household]  'Utilities - Pool Maintenance'",
"pool"  :  "[Living Expenses - Household]  'Utilities - Pool Maintenance'",
"[Living Expenses - Household]  'Utilities - POA'"  :  "[Living Expenses - Household]  'Utilities - POA'",
"poa"  :  "[Living Expenses - Household]  'Utilities - POA'",
"hoa"  :  "[Living Expenses - Household]  'Utilities - POA'",
"[Living Expenses - Household]  'Utilities - Telephone'"  :  "[Living Expenses - Household]  'Utilities - Telephone'",
"telephone"  :  "[Living Expenses - Household]  'Utilities - Telephone'",
"phone"  :  "[Living Expenses - Household]  'Utilities - Telephone'",
"[Living Expenses - Household]  'Utilities - Water'"  :  "[Living Expenses - Household]  'Utilities - Water'",
"water"  :  "[Living Expenses - Household]  'Utilities - Water'",
"[Living Expenses - Household]  'Utilities - Other'"  :  "[Living Expenses - Household]  'Utilities - Other'",
"other utilities"  :  "[Living Expenses - Household]  'Utilities - Other'",
"other util"  :  "[Living Expenses - Household]  'Utilities - Other'",
"[Living Expenses - Insurance]  'Auto Insurance'"  :  "[Living Expenses - Insurance]  'Auto Insurance'",
"auto insurance"  :  "[Living Expenses - Insurance]  'Auto Insurance'",
"[Living Expenses - Insurance]  'Home Warranty'"  :  "[Living Expenses - Insurance]  'Home Warranty'",
"[Living Expenses - Insurance]  'Life Insurance'"  :  "[Living Expenses - Insurance]  'Life Insurance'",
"[Living Expenses - Insurance]  'Long Term Care Insurance'"  :  "[Living Expenses - Insurance]  'Long Term Care Insurance'",
"ltc insurance"  :  "[Living Expenses - Insurance]  'Long Term Care Insurance'",
"ltc"  :  "[Living Expenses - Insurance]  'Long Term Care Insurance'",
"cna"  :  "[Living Expenses - Insurance]  'Long Term Care Insurance'",
"[Living Expenses - Insurance]  'Pet Insurance'"  :  "[Living Expenses - Insurance]  'Pet Insurance'",
"pet insurance"  :  "[Living Expenses - Insurance]  'Pet Insurance'",
"[Living Expenses - Insurance]  'Renters Insurance'"  :  "[Living Expenses - Insurance]  'Renters Insurance'",
"renters insurance"  :  "[Living Expenses - Insurance]  'Renters Insurance'",
"[Living Expenses - Other Discretionary]  'Biking'"  :  "[Living Expenses - Other Discretionary]  'Biking'",
"biking"  :  "[Living Expenses - Other Discretionary]  'Biking'",
"[Living Expenses - Other Discretionary]  'Books'"  :  "[Living Expenses - Other Discretionary]  'Books'",
"books"  :  "[Living Expenses - Other Discretionary]  'Books'",
"[Living Expenses - Other Discretionary]  'Cloud - hosting and software subscriptions '"  :  "[Living Expenses - Other Discretionary]  'Cloud - hosting and software subscriptions '",
"cloud"  :  "[Living Expenses - Other Discretionary]  'Cloud - hosting and software subscriptions '",
"[Living Expenses - Other Discretionary]  'Computer and electronics'"  :  "[Living Expenses - Other Discretionary]  'Computer and electronics'",
"electronics"  :  "[Living Expenses - Other Discretionary]  'Computer and electronics'",
"[Living Expenses - Other Discretionary]  'Christmas'"  :  "[Living Expenses - Other Discretionary]  'Christmas'",
"xmas"  :  "[Living Expenses - Other Discretionary]  'Christmas'",
"[Living Expenses - Other Discretionary]  'Dining and Food Out'"  :  "[Living Expenses - Other Discretionary]  'Dining and Food Out'",
"dining"  :  "[Living Expenses - Other Discretionary]  'Dining and Food Out'",
"eating out"  :  "[Living Expenses - Other Discretionary]  'Dining and Food Out'",
"food out"  :  "[Living Expenses - Other Discretionary]  'Dining and Food Out'",
"[Living Expenses - Other Discretionary]  'Entertainment and Recreation'"  :  "[Living Expenses - Other Discretionary]  'Entertainment and Recreation'",
"fun"  :  "[Living Expenses - Other Discretionary]  'Entertainment and Recreation'",
"[Living Expenses - Other Discretionary]  'Gifts'"  :  "[Living Expenses - Other Discretionary]  'Gifts'",
"gifts"  :  "[Living Expenses - Other Discretionary]  'Gifts'",
"[Living Expenses - Other Discretionary]  'Gifts - Charitable'"  :  "[Living Expenses - Other Discretionary]  'Gifts - Charitable'",
"charity"  :  "[Living Expenses - Other Discretionary]  'Gifts - Charitable'",
"[Living Expenses - Other Discretionary]  'Infotainment Subscriptions'"  :  "[Living Expenses - Other Discretionary]  'Infotainment Subscriptions'",
"infotainment"  :  "[Living Expenses - Other Discretionary]  'Infotainment Subscriptions'",
"[Living Expenses - Other Discretionary]  'Loans to Chela'"  :  "[Living Expenses - Other Discretionary]  'Loans to Chela'",
"[Living Expenses - Other Discretionary]  'Miscellaneous'"  :  "[Living Expenses - Other Discretionary]  'Miscellaneous'",
"misc"  :  "[Living Expenses - Other Discretionary]  'Miscellaneous'",
"[Living Expenses - Other Discretionary]  'Office Supplies'"  :  "[Living Expenses - Other Discretionary]  'Office Supplies'",
"office"  :  "[Living Expenses - Other Discretionary]  'Office Supplies'",
"[Living Expenses - Other Discretionary]  'Other'"  :  "[Living Expenses - Other Discretionary]  'Other'",
"other"  :  "[Living Expenses - Other Discretionary]  'Other'",
"[Living Expenses - Other Discretionary]  'Other Unallocated'"  :  "[Living Expenses - Other Discretionary]  'Other Unallocated'",
"[Living Expenses - Other Discretionary]  'Personal Care'"  :  "[Living Expenses - Other Discretionary]  'Personal Care'",
"pers care"  :  "[Living Expenses - Other Discretionary]  'Personal Care'",
"[Living Expenses - Other Discretionary]  'Personal Development'"  :  "[Living Expenses - Other Discretionary]  'Personal Development'",
"pers dev"  :  "[Living Expenses - Other Discretionary]  'Personal Development'",
"[Living Expenses - Other Discretionary]  'Personal Services'"  :  "[Living Expenses - Other Discretionary]  'Personal Services'",
"pers services"  :  "[Living Expenses - Other Discretionary]  'Personal Services'",
"pers srvc"  :  "[Living Expenses - Other Discretionary]  'Personal Services'",
"[Living Expenses - Other Discretionary]  'Professional and Career Services'"  :  "[Living Expenses - Other Discretionary]  'Professional and Career Services'",
"[Living Expenses - Other Discretionary]  'Yoga'"  :  "[Living Expenses - Other Discretionary]  'Yoga'",
"yoga"  :  "[Living Expenses - Other Discretionary]  'Yoga'",
"[Living Expenses - Other Discretionary]  'Yoga Inc'"  :  "[Living Expenses - Other Discretionary]  'Yoga Inc'",
"yoga inc"  :  "[Living Expenses - Other Discretionary]  'Yoga Inc'",
"[Living Expenses - Other Non-Discretionary]  'Bank Charges'"  :  "[Living Expenses - Other Non-Discretionary]  'Bank Charges'",
"bank"  :  "[Living Expenses - Other Non-Discretionary]  'Bank Charges'",
"[Living Expenses - Other Non-Discretionary]  'Clothing'"  :  "[Living Expenses - Other Non-Discretionary]  'Clothing'",
"clothes"  :  "[Living Expenses - Other Non-Discretionary]  'Clothing'",
"[Living Expenses - Other Non-Discretionary]  'Fitness'"  :  "[Living Expenses - Other Non-Discretionary]  'Fitness'",
"fitness"  :  "[Living Expenses - Other Non-Discretionary]  'Fitness'",
"[Living Expenses - Other Non-Discretionary]  'Fraud'"  :  "[Living Expenses - Other Non-Discretionary]  'Fraud'",
"Fraud"  :  "[Living Expenses - Other Non-Discretionary]  'Fraud'",
"[Living Expenses - Other Non-Discretionary]  'Groceries'"  :  "[Living Expenses - Other Non-Discretionary]  'Groceries'",
"grocs"  :  "[Living Expenses - Other Non-Discretionary]  'Groceries'",
"[Living Expenses - Other Non-Discretionary]  'Interest - 17008 HELOC'"  :  "[Living Expenses - Other Non-Discretionary]  'Interest - 17008 HELOC'",
"[Living Expenses - Other Non-Discretionary]  'Legal Fees'"  :  "[Living Expenses - Other Non-Discretionary]  'Legal Fees'",
"legal"  :  "[Living Expenses - Other Non-Discretionary]  'Legal Fees'",
"[Living Expenses - Other Non-Discretionary]  'Pet Expenses'"  :  "[Living Expenses - Other Non-Discretionary]  'Pet Expenses'",
"pet"  :  "[Living Expenses - Other Non-Discretionary]  'Pet Expenses'",
"[Other - Non Right Capital]  'Abt Expenses'"  :  "[Other - Non Right Capital]  'Abt Expenses'",
"[Other - Non Right Capital]  'Contingency and Unbudgetted'"  :  "[Other - Non Right Capital]  'Contingency and Unbudgetted'",
"[Other - Non Right Capital]  Flo's Expenses"  :  "[Other - Non Right Capital]  Flo's Expenses",
"flo"  :  "[Other - Non Right Capital]  Flo's Expenses",
"[Other - Non Right Capital]  'Other Non Right Capital'"  :  "[Other - Non Right Capital]  'Other Non Right Capital'",
"[Other - Non Right Capital]  'Pact Work Expenses'"  :  "[Other - Non Right Capital]  'Pact Work Expenses'",
"pact"  :  "[Other - Non Right Capital]  'Pact Work Expenses'",
"[Other - Non Right Capital]  'Taxes'"  :  "[Other - Non Right Capital]  'Taxes'",
"taxes"  :  "[Other - Non Right Capital]  'Taxes'",
"[Credit Card Payments]  'Citibank AT&T Visa'"  :  "[Credit Card Payments]  'Citibank AT&T Visa'",
"[Credit Card Payments]  'Capital One REI MasterCard'"  :  "[Credit Card Payments]  'Capital One REI MasterCard'",
"[Credit Card Payments]  'USAA Everyday Visa'"  :  "[Credit Card Payments]  'USAA Everyday Visa'",
"[Credit Card Payments]  'USAA Autopay Visa'"  :  "[Credit Card Payments]  'USAA Autopay Visa'",
"[Credit Card Payments]  'USAA Work Visa'"  :  "[Credit Card Payments]  'USAA Work Visa'",
"[Credit Card Payments]  'USAA HELOC'"  :  "[Credit Card Payments]  'USAA HELOC'",
"[Internal Master Category]  'Inflow: Ready to Assign'"  :  "[Internal Master Category]  'Inflow: Ready to Assign'",
"in"  :  "[Internal Master Category]  'Inflow: Ready to Assign'",
"[Internal Master Category]  'Deferred Income SubCategory'"  :  "[Internal Master Category]  'Deferred Income SubCategory'",
"[Internal Master Category]  'Uncategorized'"  :  "[Internal Master Category]  'Uncategorized'"


}
